camunda/__init__.py
camunda/client/__init__.py
camunda/client/engine_client.py
camunda/client/external_task_client.py
camunda/external_task/__init__.py
camunda/external_task/external_task.py
camunda/external_task/external_task_result.py
camunda/external_task/external_task_worker.py
camunda/utils/__init__.py
camunda/utils/log_utils.py
camunda/utils/response_utils.py
camunda/utils/utils.py
camunda/variables/__init__.py
camunda/variables/variables.py
avikom_camunda_client-0.10.0.dist-info/LICENSE
avikom_camunda_client-0.10.0.dist-info/METADATA
avikom_camunda_client-0.10.0.dist-info/WHEEL
avikom_camunda_client-0.10.0.dist-info/RECORD
