Metadata-Version: 2.1
Name: avikom-camunda-client
Version: 0.10.0
Summary: A python client for Camunda to process external service tasks.
Home-page: https://www.avikom.app
License: Apache-2.0
Keywords: camunda,client,service task,external task,async
Author: Alexander Neumann
Author-email: aleneum@gmail.com
Requires-Python: >=3.7.2,<3.11
Classifier: Intended Audience :: Developers
Classifier: License :: OSI Approved :: Apache Software License
Classifier: Programming Language :: Python :: 3
Classifier: Programming Language :: Python :: 3.8
Classifier: Programming Language :: Python :: 3.9
Classifier: Programming Language :: Python :: 3.10
Classifier: Programming Language :: Python :: 3
Classifier: Programming Language :: Python :: 3.7
Classifier: Programming Language :: Python :: 3.8
Classifier: Programming Language :: Python :: 3.9
Classifier: Topic :: Software Development :: Libraries
Requires-Dist: aiohttp (>=3.7.4,<4.0.0)
Project-URL: Repository, https://github.com/OpenAvikom/camunda-client
